LICENSE.txt
README.txt
setup.py
doc/Makefile
doc/apidoc-app.rst
doc/apidoc-auth.rst
doc/apidoc-client.rst
doc/apidoc-commandline.rst
doc/apidoc-memorystore.rst
doc/apidoc-server.rst
doc/apidoc-services.rst
doc/apidoc-utils.rst
doc/apps.rst
doc/client.rst
doc/conf.py
doc/deploy.rst
doc/index.rst
doc/installation.rst
doc/jython.rst
doc/make.bat
doc/projects.rst
doc/server.rst
doc/services.rst
doc/troubleshooting.rst
exampleproject/apps/fileserver/fileserver.py
exampleproject/apps/fileserver/willeapp.properties
exampleproject/apps/fileserver/shared/index.html
exampleproject/apps/requestsniffer/requestsniffer.py
exampleproject/apps/requestsniffer/willeapp.properties
exampleproject/services/requestsniffer/servicerequestsniffer.py
exampleproject/services/requestsniffer/willeservice.properties
exampleproject/services/tidy/LICENSE.txt
exampleproject/services/tidy/tidy
exampleproject/services/tidy/tidy.exe
exampleproject/services/tidy/willeservice.properties
exampleproject/services/weather/weather.py
exampleproject/services/weather/willeservice.properties
exampleproject/services/xml2json/run-xml2json.py
exampleproject/services/xml2json/willeservice.properties
exampleproject/services/xml2json/xml2json.py
scripts/wille-admin.py
scripts/wille-server.py
tests/__init__.py
tests/client_tests.py
tests/exec_grouped.py
tests/exec_services.py
tests/http_exec.py
tests/http_search.py
tests/http_timeout.py
tests/http_upload_size.py
tests/keyring_tests.py
tests/memorystore_tests.py
tests/test.keyring
tests/zipblob-test.py
tests/data/catalog.xml
tests/data/cdcatalog.xsl
tests/data/copy-everything.xsl
tests/data/data.txt
tests/data/illformed.html
tests/data/mvc.png
tests/data/valid-with-entities.html
tests/data/image/vizster.gif
tests/stub/stub.py
tests/stub/willeservice.properties
tests/timeout_test/timeout_test.py
tests/timeout_test/willeservice.properties
tests/upload_test/__init__.py
tests/upload_test/upload_test.py
tests/upload_test/willeservice.properties
wille/__init__.py
wille.egg-info/PKG-INFO
wille.egg-info/SOURCES.txt
wille.egg-info/dependency_links.txt
wille.egg-info/requires.txt
wille.egg-info/top_level.txt
