Metadata-Version: 1.0
Name: wille
Version: 2.3
Summary: Wille Visualisation Framework
Home-page: http://packages.python.org/wille
Author: TUT / Hypermedia Laboratory
Author-email: jaakko.salonen@tut.fi
License: BSD
Keywords: visualisation framework
Platform: UNKNOWN
Classifier: Development Status :: 5 - Production/Stable
Classifier: Topic :: Scientific/Engineering :: Visualization
Classifier: License :: OSI Approved :: BSD License
